torchxai/__init__.py
torchxai/explainers/__init__.py
torchxai/explainers/_utils.py
torchxai/explainers/explainer.py
torchxai/explainers/factory.py
torchxai/explainers/random.py
torchxai/explainers/_grad/deeplift.py
torchxai/explainers/_grad/deeplift_shap.py
torchxai/explainers/_grad/gradient_shap.py
torchxai/explainers/_grad/guided_backprop.py
torchxai/explainers/_grad/input_x_gradient.py
torchxai/explainers/_grad/integrated_gradients.py
torchxai/explainers/_grad/noise_tunnel.py
torchxai/explainers/_grad/saliency.py
torchxai/explainers/_perturbation/feature_ablation.py
torchxai/explainers/_perturbation/kernel_shap.py
torchxai/explainers/_perturbation/lime.py
torchxai/explainers/_perturbation/lime_base.py
torchxai/explainers/_perturbation/occlusion.py
torchxai/metrics/__init__.py
torchxai/metrics/_utils/batching.py
torchxai/metrics/_utils/common.py
torchxai/metrics/_utils/perturbation.py
torchxai/metrics/_utils/visualization.py
torchxai/metrics/axiomatic/completeness.py
torchxai/metrics/axiomatic/input_invariance.py
torchxai/metrics/axiomatic/monotonicity_corr_and_non_sens.py
torchxai/metrics/axiomatic/utilities.py
torchxai/metrics/axiomatic/multi_target/completeness.py
torchxai/metrics/axiomatic/multi_target/input_invariance.py
torchxai/metrics/axiomatic/multi_target/monotonicity_corr_and_non_sens.py
torchxai/metrics/complexity/complexity_entropy.py
torchxai/metrics/complexity/complexity_sundararajan.py
torchxai/metrics/complexity/effective_complexity.py
torchxai/metrics/complexity/sparseness.py
torchxai/metrics/faithfulness/abpc.py
torchxai/metrics/faithfulness/aopc.py
torchxai/metrics/faithfulness/faithfulness_corr.py
torchxai/metrics/faithfulness/faithfulness_estimate.py
torchxai/metrics/faithfulness/infidelity.py
torchxai/metrics/faithfulness/monotonicity.py
torchxai/metrics/faithfulness/selectivity.py
torchxai/metrics/faithfulness/sensitivity_n.py
torchxai/metrics/faithfulness/multi_target/faithfulness_corr.py
torchxai_tools-1.0.3.dist-info/licenses/LICENSE.txt
torchxai_tools-1.0.3.dist-info/METADATA
torchxai_tools-1.0.3.dist-info/WHEEL
torchxai_tools-1.0.3.dist-info/top_level.txt
torchxai_tools-1.0.3.dist-info/RECORD
