Metadata-Version: 2.4
Name: torchxai-tools
Version: 1.0.3
Summary: TorchXAI is a PyTorch-based toolkit designed for evaluating machine learning models using explainability techniques.
Author-email: Saifullah <saifullah.saifullah@dfki.de>
Maintainer-email: Saifullah <saifullah.saifullah@dfki.de>
License: MIT License
Project-URL: Homepage, https://github.com/saifullah3396/torchxai/
Project-URL: Bug Reports, https://github.com/saifullah3396/torchxai/
Project-URL: Source, https://github.com/saifullah3396/torchxai/
Keywords: torch,explainable-ai,interpretability,machine-learning,deep-learning
Classifier: Development Status :: 3 - Alpha
Classifier: Intended Audience :: Developers
Classifier: License :: OSI Approved :: MIT License
Classifier: Programming Language :: Python :: 3
Classifier: Programming Language :: Python :: 3.8
Classifier: Programming Language :: Python :: 3.9
Classifier: Programming Language :: Python :: 3.10
Classifier: Programming Language :: Python :: 3.11
Classifier: Programming Language :: Python :: 3 :: Only
Requires-Python: ==3.11.5
License-File: LICENSE.txt
Requires-Dist: hydra-core>=1.3.2
Requires-Dist: omegaconf>=2.3.0
Requires-Dist: pytorch-ignite>=0.5.0.post2
Requires-Dist: torch==2.1.2
Requires-Dist: tqdm>=4.66.4
Requires-Dist: captum==0.7.0
Requires-Dist: pandas>=2.0.3
Requires-Dist: scipy>=1.10.1
Provides-Extra: test
Requires-Dist: coverage; extra == "test"
Dynamic: license-file
